{"is_source_file": true, "format": "TypeScript", "description": "This file serves as the entry point for a Remotion-based project, registering the root React component for rendering a video.", "external_files": ["./Root"], "external_methods": ["registerRoot"], "published": ["registerRoot"], "classes": [], "methods": [{"name": "registerRoot", "description": "Registers the main React component (RemotionRoot) as the root of the Remotion video rendering process."}], "calls": ["registerRoot(RemotionRoot)"], "search-terms": ["Remotion", "entry file", "registerRoot", "React root", "video rendering"], "state": 2, "file_id": 8, "knowledge_revision": 25, "git_revision": "31f7f7008a07cb4ab1a353885c66e10f1e5eec14", "ctags": [], "hash": "6c2ce436880cb16c98160769ed0f6150", "format-version": 4, "code-base-name": "todo_frontend", "filename": "todo_frontend/src/index.ts", "revision_history": [{"25": "31f7f7008a07cb4ab1a353885c66e10f1e5eec14"}]}